docker_check/__init__.py
docker_check/checker.py
docker_check-0.0.3.dist-info/METADATA
docker_check-0.0.3.dist-info/WHEEL
docker_check-0.0.3.dist-info/top_level.txt
docker_check-0.0.3.dist-info/version.txt
docker_check-0.0.3.dist-info/RECORD
